{
  "plato": [
    {
      "id": 1,
      "nombre": "Ceviche de Pescado",
      "descripcion": "Elaborado pescado fresco con limones del norte.",
      "precio": 20
    },
    {
      "id": 2,
      "nombre": "Causa de Atun",
      "descripcion": "Rica causa de atun con verduras frescas.",
      "precio": 13
    },
    {
      "id": 3,
      "nombre": "Arroz con Pollo",
      "descripcion": "Rico arroz con pollo parte pierna.",
      "precio": 16
    },
    {
      "id": 4,
      "nombre": "La beba Desi",
      "descripcion": "Rico Plato con altas Proteinas",
      "precio": 60
    },
    {
      "id": 5,
      "nombre": "Hola ",
      "descripcion": "Holas",
      "precio": 6
    },
    {
      "id": 6,
      "nombre": "Cau Cau",
      "descripcion": "Rico",
      "precio": 56
    },
    {
      "id": 7,
      "nombre": "Arroz Chaufa ",
      "descripcion": "Rico",
      "precio": 23
    }
  ]
}